{
    "team": [
        {
            "species": "cobblemon:cryogonal",
            "gender": "GENDERLESS",
            "level": 50,
            "nature": "cobblemon:hardy",
            "ability": "levitate",
            "moveset": [
                "iceshard",
                "sheercold",
                "flashcannon",
                "blizzard"
            ],
            "ivs": {
                "hp": 31,
                "attack": 31,
                "defence": 31,
                "special_attack": 31,
                "special_defence": 31,
                "speed": 31
            },
            "evs": {
                "hp": 85,
                "attack": 85,
                "defence": 85,
                "special_attack": 85,
                "special_defence": 85,
                "speed": 85
            },
            "shiny": false,
            "heldItem": "cobblemon:wide_lens"
        },
        {
            "species": "cobblemon:beartic",
            "gender": "FEMALE",
            "level": 50,
            "nature": "cobblemon:hardy",
            "ability": "snowcloak",
            "moveset": [
                "swordsdance",
                "substitute",
                "focuspunch",
                "iciclecrash"
            ],
            "ivs": {
                "hp": 31,
                "attack": 31,
                "defence": 31,
                "special_attack": 31,
                "special_defence": 31,
                "speed": 31
            },
            "evs": {
                "hp": 85,
                "attack": 85,
                "defence": 85,
                "special_attack": 85,
                "special_defence": 85,
                "speed": 85
            },
            "shiny": false,
            "heldItem": "cobblemon:brightpowder"
        },
        {
            "species": "cobblemon:vanilluxe",
            "gender": "MALE",
            "level": 50,
            "nature": "cobblemon:hardy",
            "ability": "icebody",
            "moveset": [
                "hail",
                "weatherball",
                "protect",
                "blizzard"
            ],
            "ivs": {
                "hp": 31,
                "attack": 31,
                "defence": 31,
                "special_attack": 31,
                "special_defence": 31,
                "speed": 31
            },
            "evs": {
                "hp": 85,
                "attack": 85,
                "defence": 85,
                "special_attack": 85,
                "special_defence": 85,
                "speed": 85
            },
            "shiny": false,
            "heldItem": "cobblemon:leftovers"
        },
        {
            "species": "cobblemon:weavile",
            "gender": "MALE",
            "level": 50,
            "nature": "cobblemon:hardy",
            "ability": "pressure",
            "moveset": [
                "nightslash",
                "fakeout",
                "brickbreak",
                "iceshard"
            ],
            "ivs": {
                "hp": 31,
                "attack": 31,
                "defence": 31,
                "special_attack": 31,
                "special_defence": 31,
                "speed": 31
            },
            "evs": {
                "hp": 85,
                "attack": 85,
                "defence": 85,
                "special_attack": 85,
                "special_defence": 85,
                "speed": 85
            },
            "shiny": false,
            "heldItem": "cobblemon:focus_sash"
        },
        {
            "species": "cobblemon:dewgong",
            "gender": "MALE",
            "level": 50,
            "nature": "cobblemon:hardy",
            "ability": "hydration",
            "moveset": [
                "fakeout",
                "drillrun",
                "aquajet",
                "frostbreath"
            ],
            "ivs": {
                "hp": 31,
                "attack": 31,
                "defence": 31,
                "special_attack": 31,
                "special_defence": 31,
                "speed": 31
            },
            "evs": {
                "hp": 85,
                "attack": 85,
                "defence": 85,
                "special_attack": 85,
                "special_defence": 85,
                "speed": 85
            },
            "shiny": false,
            "heldItem": "cobblemon:life_orb"
        },
        {
            "species": "cobblemon:walrein",
            "gender": "FEMALE",
            "level": 50,
            "nature": "cobblemon:hardy",
            "ability": "icebody",
            "moveset": [
                "earthquake",
                "superfang",
                "aquatail",
                "avalanche"
            ],
            "ivs": {
                "hp": 31,
                "attack": 31,
                "defence": 31,
                "special_attack": 31,
                "special_defence": 31,
                "speed": 31
            },
            "evs": {
                "hp": 85,
                "attack": 85,
                "defence": 85,
                "special_attack": 85,
                "special_defence": 85,
                "speed": 85
            },
            "shiny": false,
            "heldItem": "cobblemon:expert_belt"
        }
    ]
}